print_ilo.py
testilo-0.0.4.dist-info/METADATA
testilo-0.0.4.dist-info/WHEEL
testilo-0.0.4.dist-info/top_level.txt
testilo-0.0.4.dist-info/RECORD
