Metadata-Version: 2.1
Name: testilo
Version: 0.0.4
Summary: lib test for ilo
Home-page: https://github.com/ilorobot/python-library
Author: ilo robot (SLB)
Author-email: <ilotherobot@gmail.com>
License: UNKNOWN
Platform: UNKNOWN
